grubhub/__init__.py
grubhub/train.py
grubhub/utils.py
src/__init__.py
src/train.py
src/utils.py
tests/test_utils.py
mallen_grubhub_test-1.1.0.dist-info/METADATA
mallen_grubhub_test-1.1.0.dist-info/WHEEL
mallen_grubhub_test-1.1.0.dist-info/entry_points.txt
mallen_grubhub_test-1.1.0.dist-info/top_level.txt
mallen_grubhub_test-1.1.0.dist-info/RECORD
