Metadata-Version: 2.1
Name: mallen-grubhub-test
Version: 1.1.0
Summary: A small module to train and save a classifier.
Home-page: https://github.com/brentonmallen1/grubhub_test
Author: Brenton Mallen
Author-email: brentonmallen1@gmail.com
License: MIT
Keywords: model train save
Platform: UNKNOWN
Classifier: Programming Language :: Python :: 3.6
Requires-Python: >=3.6
Requires-Dist: pandas (>=0.23.4)
Requires-Dist: scikit-learn (>=0.20)
Requires-Dist: click (>=7.0)
